[
    {
      "brand":"Acer nitro 5",
      "model":"AN505",
      "description":"Ryzen 5 6000s, GeForce RTX 3060 6gb, PCIe Gen 4 SSD 512gb, Full HD 144 Hz",
      "price":500000
    },
    {
        "brand": "Acer Nitro 5",
        "model": "AN535",
        "description": "Intel Core i7 12th Gen, AMD Radeon RX 6600M 6gb, 1TB HDD + 512GB SSD, Full HD 144 Hz",
        "price": 950000
      },
    {
        "brand": "HP Pavilion",
        "model": "Pavilion 15",
        "description": "Intel Core i7 11th Gen, NVIDIA GTX 1650 4gb, 1TB HDD + 512GB SSD, Full HD 120 Hz",
        "price": 750000
    },
    {
        "brand": "Dell G5",
        "model": "G5 5500",
        "description": "AMD Ryzen 7 7000s, Radeon RX 6700M 8gb, PCIe Gen 4 SSD 1TB, QHD 165 Hz",
        "price": 920000
    },      
    {
        "brand": "Dell G5",
        "model": "G5 5500",
        "description": "AMD Ryzen 7 7000s, Radeon RX 6700M 8gb, PCIe Gen 4 SSD 1TB, QHD 165 Hz",
        "price": 920000
      },
      {
        "brand": "Asus ROG",
        "model": "ROG Strix G17",
        "description": "AMD Ryzen 9 8000s, GeForce RTX 3070 8gb, PCIe Gen 4 SSD 2TB, 4K OLED 120 Hz",
        "price": 1250000
      },
      {
        "brand": "MSI Bravo",
        "model": "Bravo 15",
        "description": "Intel Core i7 12th Gen, AMD Radeon RX 6600M 6gb, 1TB HDD + 512GB SSD, Full HD 144 Hz",
        "price": 970000
      },
      {
        "brand": "Acer Predator",
        "model": "Predator Helios 300",
        "description": "AMD Ryzen 5 9000s, NVIDIA GTX 1650 4gb, 256GB NVMe SSD, Full HD 75 Hz",
        "price": 580000
      },
      {
        "brand": "Dell XPS",
        "model": "XPS 13",
        "description": "Intel Core i7 11th Gen, Intel Iris Xe Graphics, 512GB SSD, 13.4-inch 4K Ultra HD",
        "price": 1500000
      },
      {
        "brand": "Lenovo ThinkPad",
        "model": "ThinkPad X1 Carbon",
        "description": "Intel Core i5 10th Gen, Intel UHD Graphics, 256GB NVMe SSD, 14-inch Full HD",
        "price": 1200000
      }
     ,
     {
        "brand": "Asus ZenBook",
        "model": "ZenBook 14",
        "description": "AMD Ryzen 7 5000s, NVIDIA MX450 2gb, 1TB PCIe SSD, 14-inch Full HD",
        "price": 1100000
      }
    ,
    {
        "brand": "HP Spectre",
        "model": "Spectre x360",
        "description": "Intel Core i7 12th Gen, Intel Iris Xe Graphics, 512GB SSD, 13.3-inch 4K OLED",
        "price": 1700000
      },
      {
        "brand": "Acer Swift",
        "model": "Swift 5",
        "description": "Intel Core i5 11th Gen, Intel UHD Graphics, 256GB NVMe SSD, 14-inch Full HD",
        "price": 900000
      },
      {
        "brand": "MSI Modern",
        "model": "Modern 14",
        "description": "AMD Ryzen 5 4000s, Radeon Vega 6 Graphics, 512GB NVMe SSD, 14-inch Full HD",
        "price": 800000
      },
      {
        "brand": "Apple MacBook Air",
        "model": "M2",
        "description": "Apple Silicon M2 Chip, 512GB SSD, 13.3-inch Retina Display",
        "price": 2000000
      },
      {
        "brand": "Razer Blade",
        "model": "Blade 15",
        "description": "Intel Core i9 10th Gen, NVIDIA RTX 3080 16gb, 1TB NVMe SSD, 15.6-inch QHD 240 Hz",
        "price": 2500000
      },
      {
        "brand": "LG Gram",
        "model": "Gram 17",
        "description": "Intel Core i7 11th Gen, Intel Iris Xe Graphics, 1TB NVMe SSD, 17-inch WQXGA",
        "price": 1800000
      },
      {
        "brand": "HP Envy",
        "model": "Envy x360",
        "description": "AMD Ryzen 9 6000s, Radeon RX Vega 8 Graphics, 1TB SSD, 15.6-inch Full HD Touchscreen",
        "price": 1300000
      },
      {
        "brand": "Acer Aspire",
        "model": "Aspire 5",
        "description": "Intel Core i5 11th Gen, Intel UHD Graphics, 512GB NVMe SSD, 14-inch Full HD",
        "price": 800000
      },
      {
        "brand": "Lenovo Yoga",
        "model": "Yoga C940",
        "description": "Intel Core i7 10th Gen, Intel Iris Plus Graphics, 1TB SSD, 14-inch 4K UHD Touchscreen",
        "price": 1600000
      }
      ,
      {
        "brand": "Asus ROG Zephyrus",
        "model": "Zephyrus G14",
        "description": "AMD Ryzen 9 9000s, NVIDIA RTX 3070 8gb, 1TB NVMe SSD, 14-inch QHD 120 Hz",
        "price": 2000000
      },
      {
        "brand": "Dell Inspiron",
        "model": "Inspiron 15",
        "description": "Intel Core i5 12th Gen, Intel Iris Xe Graphics, 256GB NVMe SSD, 15.6-inch Full HD",
        "price": 900000
      },
      {
        "brand": "MSI Prestige",
        "model": "Prestige 14",
        "description": "Intel Core i7 11th Gen, NVIDIA GTX 1650 4gb, 512GB NVMe SSD, 14-inch Full HD",
        "price": 1200000
      },
      {
        "brand": "Apple MacBook Pro",
        "model": "M1 Pro",
        "description": "Apple Silicon M1 Pro Chip, 512GB SSD, 16-inch Liquid Retina XDR Display",
        "price": 2800000
      }
      ,
      {
        "brand": "Razer Blade Stealth",
        "model": "Stealth 13",
        "description": "Intel Core i7 11th Gen, NVIDIA GTX 1650 Ti 4gb, 512GB NVMe SSD, 13.3-inch 4K Touchscreen",
        "price": 2300000
      }
      ,{
        "brand": "LG Gram",
        "model": "Gram 14 2-in-1",
        "description": "Intel Core i5 10th Gen, Intel Iris Plus Graphics, 512GB NVMe SSD, 14-inch Full HD Touchscreen",
        "price": 1500000
      },
        {
          "brand": "HP Envy",
          "model": "Envy x360",
          "description": "Ryzen 9 6000s, RX Vega 8, 1TB SSD, 15.6\" FHD Touch",
          "price": 1300000
        },
        {
          "brand": "Acer Aspire",
          "model": "Aspire 5",
          "description": "Core i5 11th Gen, UHD Graphics, 512GB NVMe SSD, 14\" FHD",
          "price": 800000
        },
        {
          "brand": "Lenovo Yoga",
          "model": "Yoga C940",
          "description": "Core i7 10th Gen, Iris Plus Graphics, 1TB SSD, 14\" 4K UHD Touch",
          "price": 1600000
        },
        {
          "brand": "Asus ROG Zephyrus",
          "model": "Zephyrus G14",
          "description": "Ryzen 9 9000s, RTX 3070 8gb, 1TB NVMe SSD, 14\" QHD 120 Hz",
          "price": 2000000
        },
        {
          "brand": "Dell Inspiron",
          "model": "Inspiron 15",
          "description": "Core i5 12th Gen, Iris Xe Graphics, 256GB NVMe SSD, 15.6\" FHD",
          "price": 900000
        },
        {
          "brand": "MSI Prestige",
          "model": "Prestige 14",
          "description": "Core i7 11th Gen, GTX 1650 4gb, 512GB NVMe SSD, 14\" FHD",
          "price": 1200000
        },
        {
          "brand": "Apple MacBook Pro",
          "model": "M1 Pro",
          "description": "M1 Pro Chip, 512GB SSD, 16\" Liquid Retina XDR Display",
          "price": 2800000
        },
        {
          "brand": "Razer Blade Stealth",
          "model": "Stealth 13",
          "description": "Core i7 11th Gen, GTX 1650 Ti 4gb, 512GB NVMe SSD, 13.3\" 4K Touch",
          "price": 2300000
        },
        {
          "brand": "LG Gram",
          "model": "Gram 14 2-in-1",
          "description": "Core i5 10th Gen, Iris Plus Graphics, 512GB NVMe SSD, 14\" FHD Touch",
          "price": 1500000
        }
        ,
            {
              "brand": "Dell XPS",
              "model": "XPS 15",
              "description": "Core i9 11th Gen, NVIDIA RTX 3070 8gb, 1TB NVMe SSD, 15.6\" 4K OLED",
              "price": 2500000
            },
            {
              "brand": "Lenovo Legion",
              "model": "Legion 7",
              "description": "Ryzen 9 7000s, RTX 3080 16gb, 2TB NVMe SSD, 17.3\" QHD 165 Hz",
              "price": 3000000
            },
            {
              "brand": "Asus VivoBook",
              "model": "VivoBook S14",
              "description": "Core i5 12th Gen, Intel UHD Graphics, 512GB NVMe SSD, 14\" FHD",
              "price": 1100000
            },
            {
              "brand": "HP Omen",
              "model": "Omen 15",
              "description": "Ryzen 7 6000s, GTX 1660 Ti 6gb, 1TB HDD + 256GB SSD, 15.6\" FHD 144 Hz",
              "price": 1800000
            },
            {
              "brand": "Acer Swift",
              "model": "Swift 3",
              "description": "Core i7 11th Gen, Intel Iris Xe Graphics, 512GB NVMe SSD, 13.5\" QHD",
              "price": 1500000
            },
            {
              "brand": "MSI GE",
              "model": "GE66 Raider",
              "description": "Core i9 10th Gen, RTX 2080 Super 8gb, 2TB NVMe SSD, 15.6\" FHD 300 Hz",
              "price": 3500000
            },
            {
              "brand": "Apple MacBook Air",
              "model": "M2",
              "description": "M2 Chip, 512GB SSD, 13.3\" Retina Display",
              "price": 2000000
            },
            {
              "brand": "Razer Blade",
              "model": "Blade 17",
              "description": "Core i7 12th Gen, RTX 3080 16gb, 2TB NVMe SSD, 17.3\" 4K OLED 120 Hz",
              "price": 4000000
            },
            {
              "brand": "LG Gram",
              "model": "Gram 17",
              "description": "Core i7 11th Gen, Intel Iris Xe Graphics, 1TB NVMe SSD, 17\" WQXGA",
              "price": 2000000
            }
  ]
  